jacquard/__init__.py
jacquard/__main__.py
jacquard/cli.py
jacquard/commands.py
jacquard/commands_dev.py
jacquard/config.py
jacquard/constants.py
jacquard/plugin.py
jacquard/utils.py
jacquard/utils_dev.py
jacquard/wsgi.py
jacquard/buckets/__init__.py
jacquard/buckets/commands.py
jacquard/buckets/constants.py
jacquard/buckets/entry.py
jacquard/buckets/exceptions.py
jacquard/buckets/models.py
jacquard/buckets/utils.py
jacquard/constraints/__init__.py
jacquard/directory/__init__.py
jacquard/directory/base.py
jacquard/directory/commands.py
jacquard/directory/django.py
jacquard/directory/dummy.py
jacquard/directory/union.py
jacquard/directory/utils.py
jacquard/experiments/__init__.py
jacquard/experiments/commands.py
jacquard/experiments/experiment.py
jacquard/odm/__init__.py
jacquard/odm/base.py
jacquard/odm/fields.py
jacquard/odm/session.py
jacquard/odm/utils.py
jacquard/odm/inflection/__init__.py
jacquard/service/__init__.py
jacquard/service/base.py
jacquard/service/commands.py
jacquard/service/endpoints.py
jacquard/service/wsgi.py
jacquard/storage/__init__.py
jacquard/storage/base.py
jacquard/storage/cloned_redis.py
jacquard/storage/commands.py
jacquard/storage/dummy.py
jacquard/storage/exceptions.py
jacquard/storage/file.py
jacquard/storage/redis.py
jacquard/storage/testing_utils.py
jacquard/storage/utils.py
jacquard/users/__init__.py
jacquard/users/commands.py
jacquard/users/settings.py
jacquard_split-0.7.0.dist-info/COPYING
jacquard_split-0.7.0.dist-info/METADATA
jacquard_split-0.7.0.dist-info/WHEEL
jacquard_split-0.7.0.dist-info/entry_points.txt
jacquard_split-0.7.0.dist-info/top_level.txt
jacquard_split-0.7.0.dist-info/RECORD
